cxx11bindings/__init__.py
pycxx11bindings-1.2.1.dist-info/licenses/LICENSE
pycxx11bindings-1.2.1.dist-info/METADATA
pycxx11bindings-1.2.1.dist-info/WHEEL
pycxx11bindings-1.2.1.dist-info/top_level.txt
pycxx11bindings-1.2.1.dist-info/RECORD
