Metadata-Version: 2.4
Name: PyCxx11Bindings
Version: 1.2.1
License: MIT
Project-URL: Changelog, https://github.com/dicomstudio/PyCxx11Bindings/blob/dev/CHANGELOG.md
Project-URL: Documentation, https://dicomstudio.github.io/PyCxx11Bindings
Project-URL: Issues, https://github.com/dicomstudio/PyCxx11Bindings/issues
Project-URL: Repository, https://github.com/dicomstudio/PyCxx11Bindings
Classifier: Programming Language :: Python :: 3.8
Classifier: Programming Language :: Python :: 3.9
Classifier: Programming Language :: Python :: 3.10
Classifier: Programming Language :: Python :: 3.11
Classifier: Programming Language :: Python :: 3.13
Requires-Python: <3.14,>=3.8
License-File: LICENSE
Provides-Extra: develop
Requires-Dist: PyCxx11Bindings[test]; extra == "develop"
Requires-Dist: commitizen; extra == "develop"
Requires-Dist: ipykernel; extra == "develop"
Requires-Dist: pre-commit; extra == "develop"
Requires-Dist: pylsp-rope; extra == "develop"
Requires-Dist: python-lsp-ruff; extra == "develop"
Requires-Dist: python-lsp-server[all]; extra == "develop"
Requires-Dist: ruff; extra == "develop"
Provides-Extra: docs
Requires-Dist: pdoc; extra == "docs"
Provides-Extra: test
Requires-Dist: pytest; extra == "test"
Requires-Dist: pytest-xdist; extra == "test"
Dynamic: license-file
